Metadata-Version: 2.1
Name: php-var-dump
Version: 0.3.2
Summary: A port of the var_dump function of PHP to Python. This lets you make PHP files with Python.
Home-page: http://github.com/jvanasco/php_var_dump
Author: Jonathan Vanasco
Author-email: jonathan@findmeon.com
License: BSD
Platform: UNKNOWN
Classifier: License :: OSI Approved :: BSD License
Classifier: Programming Language :: PHP
Classifier: Programming Language :: Python
Classifier: Programming Language :: Python :: 2
Classifier: Programming Language :: Python :: 3
Provides-Extra: testing
